JavaApiBanbenDeVertXCoreShouce/README.md
JavaApiBanbenDeVertXCoreShouce/__init__.py
JavaApiBanbenDeVertXCoreShouce/__main__.py
JavaApiBanbenDeVertXCoreShouce/file.epub
JavaApiBanbenDeVertXCoreShouce/index.html
JavaApiBanbenDeVertXCoreShouce/css/__init__.py
JavaApiBanbenDeVertXCoreShouce/css/annotations.css
JavaApiBanbenDeVertXCoreShouce/css/main.css
JavaApiBanbenDeVertXCoreShouce/css/normalize.css
JavaApiBanbenDeVertXCoreShouce/css/popup.css
JavaApiBanbenDeVertXCoreShouce/font/__init__.py
JavaApiBanbenDeVertXCoreShouce/font/fontello.eot
JavaApiBanbenDeVertXCoreShouce/font/fontello.svg
JavaApiBanbenDeVertXCoreShouce/font/fontello.ttf
JavaApiBanbenDeVertXCoreShouce/font/fontello.woff
JavaApiBanbenDeVertXCoreShouce/img/__init__.py
JavaApiBanbenDeVertXCoreShouce/img/annotator-glyph-sprite.png
JavaApiBanbenDeVertXCoreShouce/img/annotator-icon-sprite.png
JavaApiBanbenDeVertXCoreShouce/img/apple-touch-icon.png
JavaApiBanbenDeVertXCoreShouce/img/cancelfullscreen.png
JavaApiBanbenDeVertXCoreShouce/img/close.png
JavaApiBanbenDeVertXCoreShouce/img/fullscreen.png
JavaApiBanbenDeVertXCoreShouce/img/loader.gif
JavaApiBanbenDeVertXCoreShouce/img/menu-icon.png
JavaApiBanbenDeVertXCoreShouce/img/save.png
JavaApiBanbenDeVertXCoreShouce/img/saved.png
JavaApiBanbenDeVertXCoreShouce/img/settings-s.png
JavaApiBanbenDeVertXCoreShouce/img/settings.png
JavaApiBanbenDeVertXCoreShouce/img/star.png
JavaApiBanbenDeVertXCoreShouce/js/__init__.py
JavaApiBanbenDeVertXCoreShouce/js/epub.js
JavaApiBanbenDeVertXCoreShouce/js/epub.min.js
JavaApiBanbenDeVertXCoreShouce/js/epub.min.map
JavaApiBanbenDeVertXCoreShouce/js/hooks.min.js
JavaApiBanbenDeVertXCoreShouce/js/hooks.min.map
JavaApiBanbenDeVertXCoreShouce/js/reader.js
JavaApiBanbenDeVertXCoreShouce/js/reader.js.map
JavaApiBanbenDeVertXCoreShouce/js/reader.min.js
JavaApiBanbenDeVertXCoreShouce/js/reader.min.map
JavaApiBanbenDeVertXCoreShouce/js/hooks/__init__.py
JavaApiBanbenDeVertXCoreShouce/js/hooks/extensions/__init__.py
java_api_banben_de_vert_x_core_shouce-2024.3.2.0.dist-info/METADATA
java_api_banben_de_vert_x_core_shouce-2024.3.2.0.dist-info/WHEEL
java_api_banben_de_vert_x_core_shouce-2024.3.2.0.dist-info/entry_points.txt
java_api_banben_de_vert_x_core_shouce-2024.3.2.0.dist-info/top_level.txt
java_api_banben_de_vert_x_core_shouce-2024.3.2.0.dist-info/RECORD
